ecos/__init__.py
ecos_kr-0.1.0.dist-info/METADATA
ecos_kr-0.1.0.dist-info/WHEEL
ecos_kr-0.1.0.dist-info/entry_points.txt
ecos_kr-0.1.0.dist-info/top_level.txt
ecos_kr-0.1.0.dist-info/RECORD
