Metadata-Version: 2.1
Name: ecos-kr
Version: 0.1.0
Summary: 한국은행 ECOS API 클라이언트
Home-page: https://github.com/leejongwok/ecos-kr
Author: 이종욱
Author-email: eidoslibrary@adhd-infos.com
Classifier: Development Status :: 3 - Alpha
Classifier: Intended Audience :: Developers
Classifier: License :: OSI Approved :: MIT License
Classifier: Programming Language :: Python :: 3.7
Classifier: Programming Language :: Python :: 3.8
Classifier: Programming Language :: Python :: 3.9
Requires-Python: >=3.7
Requires-Dist: requests>=2.25.0
Requires-Dist: pandas>=1.2.0
Requires-Dist: pyyaml>=5.4.0
Requires-Dist: click>=7.1.2
Requires-Dist: rich>=10.0.0
Requires-Dist: beautifulsoup4>=4.9.3
Requires-Dist: lxml>=4.9.0
Requires-Dist: cryptography>=3.4.7
